amazeing123.py
amazeing123-0.0.1.dist-info/LICENSE
amazeing123-0.0.1.dist-info/METADATA
amazeing123-0.0.1.dist-info/WHEEL
amazeing123-0.0.1.dist-info/top_level.txt
amazeing123-0.0.1.dist-info/RECORD
