Metadata-Version: 2.1
Name: amazeing123
Version: 0.0.1
Summary: Maze solver slash generator requires numpy
Author: Luke Ainscow
License: UNKNOWN
Platform: UNKNOWN
Classifier: Programming Language :: Python :: 3
Classifier: License :: OSI Approved :: MIT License
Classifier: Operating System :: OS Independent
Requires-Python: >=3.6
License-File: LICENSE
